hto_dnd/__init__.py
hto_dnd/cli.py
hto_dnd/demux_dsb.py
hto_dnd/dsb_algorithm.py
hto_dnd/dsb_and_demux.py
hto_dnd/dsb_viz.py
hto_dnd-0.1.4.dist-info/LICENSE
hto_dnd-0.1.4.dist-info/METADATA
hto_dnd-0.1.4.dist-info/WHEEL
hto_dnd-0.1.4.dist-info/entry_points.txt
hto_dnd-0.1.4.dist-info/top_level.txt
hto_dnd-0.1.4.dist-info/RECORD
